yamllm/__init__.py
yamllm/core/__init__.py
yamllm/core/config.py
yamllm/core/llm.py
yamllm/core/parser.py
yamllm/core/utils.py
yamllm/memory/__init__.py
yamllm/memory/conversation_store.py
yamllm/tools/__init__.py
yamllm/tools/base.py
yamllm/tools/registry.py
yamllm/tools/utility_tools.py
yamllm_core-0.1.12.dist-info/METADATA
yamllm_core-0.1.12.dist-info/WHEEL
yamllm_core-0.1.12.dist-info/licenses/LICENSE
yamllm_core-0.1.12.dist-info/RECORD
