Metadata-Version: 2.4
Name: yamllm-core
Version: 0.1.12
Summary: YAML-based LLM configuration and execution
Project-URL: Homepage, https://github.com/codehalwell/yamllm
Project-URL: Documentation, https://codehalwell.github.io/yamllm/
Project-URL: Repository, https://github.com/codehalwell/yamllm.git
Author-email: Daniel Halwell <danielhalwell@gmail.com>
License: MIT
License-File: LICENSE
Classifier: Development Status :: 3 - Alpha
Classifier: Intended Audience :: Developers
Classifier: License :: OSI Approved :: MIT License
Classifier: Programming Language :: Python :: 3.10
Requires-Python: >=3.10
Requires-Dist: bs4>=0.0.2
Requires-Dist: duckduckgo-search>=7.5.5
Requires-Dist: faiss-cpu>=1.10.0
Requires-Dist: matplotlib>=3.10.0
Requires-Dist: numpy>=2.2.3
Requires-Dist: openai>=1.63.0
Requires-Dist: pandas>=2.2.3
Requires-Dist: pydantic>=2.10.6
Requires-Dist: python-dotenv>=1.0.1
Requires-Dist: pyyaml>=6.0.2
Requires-Dist: requests>=2.32.3
Requires-Dist: rich>=13.9.4
Requires-Dist: ruff>=0.9.6
Requires-Dist: scikit-learn>=1.6.1
Requires-Dist: seaborn>=0.13.2
Requires-Dist: tabulate>=0.9.0
Provides-Extra: dev
Requires-Dist: black>=24.1.1; extra == 'dev'
Requires-Dist: isort>=5.13.2; extra == 'dev'
Requires-Dist: mypy>=1.8.0; extra == 'dev'
Requires-Dist: pytest>=8.0.0; extra == 'dev'
